i3_gnome_pomodoro/pomodoro_client.py
i3_gnome_pomodoro-0.1.0.dist-info/LICENSE
i3_gnome_pomodoro-0.1.0.dist-info/METADATA
i3_gnome_pomodoro-0.1.0.dist-info/WHEEL
i3_gnome_pomodoro-0.1.0.dist-info/entry_points.txt
i3_gnome_pomodoro-0.1.0.dist-info/RECORD
