Metadata-Version: 2.1
Name: i3-gnome-pomodoro
Version: 0.1.0
Summary: 
Author: Daniel Kantor
Author-email: git@daniel-kantor.com
Requires-Python: >=3.11,<4.0
Classifier: Programming Language :: Python :: 3
Classifier: Programming Language :: Python :: 3.11
Classifier: Programming Language :: Python :: 3.12
Requires-Dist: blinkstick (>=1.2.0,<2.0.0)
Requires-Dist: click (>=8.1.7,<9.0.0)
Requires-Dist: i3ipc (>=2.2.1,<3.0.0)
Requires-Dist: pydbus (>=0.6.0,<0.7.0)
Requires-Dist: pygobject (>=3.46.0,<4.0.0)
Requires-Dist: pyusb (>=1.2.1,<2.0.0)
